cellular/__init__.py
cellular/main.py
cellular-0.0.1.dist-info/DESCRIPTION.rst
cellular-0.0.1.dist-info/METADATA
cellular-0.0.1.dist-info/RECORD
cellular-0.0.1.dist-info/WHEEL
cellular-0.0.1.dist-info/entry_points.txt
cellular-0.0.1.dist-info/metadata.json
cellular-0.0.1.dist-info/top_level.txt
