Metadata-Version: 2.0
Name: cellular
Version: 0.0.1
Summary: demos for cellular automata
Home-page: https://github.com/kemingy/cellular
Author: Keming Yang
Author-email: kemingy94@gmail.com
License: UNKNOWN
Platform: UNKNOWN
Classifier: Programming Language :: Python :: 3
Classifier: License :: OSI Approved :: MIT License
Classifier: Operating System :: OS Independent
